imagen_hub/__init__.py
imagen_hub/_version.py
imagen_hub/benchmark/__init__.py
imagen_hub/benchmark/control_guided_ig.py
imagen_hub/benchmark/mask_guided_ie.py
imagen_hub/benchmark/multi_concept_ic.py
imagen_hub/benchmark/subject_driven_ie.py
imagen_hub/benchmark/subject_driven_ig.py
imagen_hub/benchmark/text_guided_ie.py
imagen_hub/benchmark/text_guided_ig.py
imagen_hub/depend/__init__.py
imagen_hub/depend/clip_retrieval/__init__.py
imagen_hub/depend/clip_retrieval/clip_back.py
imagen_hub/depend/clip_retrieval/clip_client.py
imagen_hub/depend/clip_retrieval/clip_end2end.py
imagen_hub/depend/clip_retrieval/clip_filter.py
imagen_hub/depend/clip_retrieval/clip_front.py
imagen_hub/depend/clip_retrieval/clip_index.py
imagen_hub/depend/clip_retrieval/h14_nsfw_model.py
imagen_hub/depend/clip_retrieval/ivf_metadata_ordering.py
imagen_hub/depend/clip_retrieval/load_clip.py
imagen_hub/depend/lang_sam/__init__.py
imagen_hub/depend/lang_sam/lang_sam.py
imagen_hub/infermodels/__init__.py
imagen_hub/infermodels/auraflow.py
imagen_hub/infermodels/blended_diffusion.py
imagen_hub/infermodels/blip_diffusion.py
imagen_hub/infermodels/control_net.py
imagen_hub/infermodels/cosxl.py
imagen_hub/infermodels/custom_diffusion.py
imagen_hub/infermodels/cyclediffusion.py
imagen_hub/infermodels/dalle.py
imagen_hub/infermodels/deepfloydif.py
imagen_hub/infermodels/diffedit.py
imagen_hub/infermodels/dreambooth.py
imagen_hub/infermodels/dreamedit.py
imagen_hub/infermodels/flux.py
imagen_hub/infermodels/freecontrol.py
imagen_hub/infermodels/glide.py
imagen_hub/infermodels/hunyuan.py
imagen_hub/infermodels/imagic.py
imagen_hub/infermodels/infedit.py
imagen_hub/infermodels/instructpix2pix.py
imagen_hub/infermodels/kandinsky.py
imagen_hub/infermodels/kolors.py
imagen_hub/infermodels/photoswap.py
imagen_hub/infermodels/pix2pixzero.py
imagen_hub/infermodels/pixart_alpha.py
imagen_hub/infermodels/pixart_sigma.py
imagen_hub/infermodels/pnp.py
imagen_hub/infermodels/prompt2prompt.py
imagen_hub-0.2.4.dist-info/LICENSE
imagen_hub-0.2.4.dist-info/METADATA
imagen_hub-0.2.4.dist-info/WHEEL
imagen_hub-0.2.4.dist-info/top_level.txt
imagen_hub-0.2.4.dist-info/RECORD
