Metadata-Version: 2.1
Name: imagen_hub
Version: 0.2.4
Summary: ImagenHub is a one-stop library to standardize the inference and evaluation of all the conditional image generation models.
Home-page: https://github.com/TIGER-AI-Lab/ImagenHub
Author: Max Ku
Author-email: m3ku@uwaterloo.ca
License: MIT License
License-File: LICENSE
